{
  "_metadata": {
    "source": "True_API_GIS_MT-v553.0-11.09.2025-at-13-41-25.docx",
    "version": "553.0",
    "extracted_at": "2025-09-16",
    "toolchain": [
      "docx2txt 0.9",
      "python 3.12"
    ]
  },
  "endpoints": [
    {
      "url": "/auth/key",
      "method": "GET",
      "description": "Сервер отвечает на запрос сообщением с кодом 200 (ОК), либо сообщением об ошибке."
    },
    {
      "url": "/auth/simpleSignIn",
      "method": "POST",
      "description": "1.5.2. Получение ключа сессии при единой аутентификации"
    },
    {
      "url": "/elk/crm-api/documents",
      "method": "GET",
      "description": "2.1.2. Шаг 2: получение сведений по черновикам договоров между УОТ и ГИС МТ"
    },
    {
      "url": "/elk/crm-api/document?guid={id}",
      "method": "GET",
      "description": "2.1.3. Шаг 3: получение (выгрузка) черновиков договоров для подписания УОТ"
    },
    {
      "url": "/elk/outgoing-documents/{id}/signature",
      "method": "POST",
      "description": "2.1.4. Шаг 4: подписание договоров"
    },
    {
      "url": "/elk/outgoing-documents/{edoDocumentId}",
      "method": "GET",
      "description": "2.1.5. Шаг 5: выгрузка подписанных договоров"
    },
    {
      "url": "/participants",
      "method": "GET",
      "description": "С токеном: в ответе возвращается расширенная информация об участнике оборота товаров, если ИНН участника оборота товаров, формирующего запрос, равен ИНН, указанному в запросе."
    },
    {
      "url": "/api/v3/true-api/mods/info",
      "method": "POST",
      "description": "Тип приватности: публичный"
    },
    {
      "url": "/api/v3/true-api/mods/list",
      "method": "GET",
      "description": "Тип приватности: публичный"
    },
    {
      "url": "/api/v3/true-api/mrd/delegation/search",
      "method": "POST",
      "description": "Метод предназначен для проверки наличия машиночитаемых доверенностей, выданных пользователю, выполняющему запрос. При наличии МЧД метод возвращает о них информацию: ИНН юридического лица / индивидуального предпринимателя, которым выдана МЧД, статус, дату начала и окончания действия МЧД. Тип приватности: приватный"
    },
    {
      "url": "/elk/crm-api/documents",
      "method": "GET",
      "description": "Тип приватности: приватный"
    },
    {
      "url": "/elk/crm-api/document",
      "method": "GET",
      "description": "Тип приватности: приватный"
    },
    {
      "url": "/elk/outgoing-documents/{documentId}/signature",
      "method": "POST",
      "description": "Тип приватности: приватный"
    },
    {
      "url": "/elk/crm-api/prequests",
      "method": "POST",
      "description": "Тип приватности: приватный"
    },
    {
      "url": "/elk/product-groups/balance/all",
      "method": null,
      "description": "Тип приватности: приватный"
    },
    {
      "url": "/elk/product-groups/balance",
      "method": null,
      "description": "Тип приватности: приватный"
    },
    {
      "url": "/lk/documents/create",
      "method": "POST",
      "description": "Ограничение доступа к методу: при отправке запроса с токеном пользователя с ролью «Сотрудник» в ответе вернётся ошибка (подробнее см. в «Памятке по ролевой модели доступа Системы маркировки»)."
    },
    {
      "url": "/documents/aggregation/create",
      "method": "POST",
      "description": "Тип приватности: приватный"
    },
    {
      "url": "/api/v4/true-api/cises/search",
      "method": "POST",
      "description": "Тип приватности: c токеном авторизации"
    },
    {
      "url": "/api/v3/true-api/cises/info",
      "method": "POST",
      "description": "текущий владелец."
    },
    {
      "url": "/cises/short/list",
      "method": "POST",
      "description": "Тип приватности: публичный"
    },
    {
      "url": "/cises/eaes/info",
      "method": null,
      "description": "Республика Казахстан — товарная группа \"Обувные товары\"."
    },
    {
      "url": "/cises/eaes/check-export",
      "method": "POST",
      "description": "Тип приватности: публичный (с использованием токена)"
    },
    {
      "url": "/cises/check",
      "method": "POST",
      "description": "Метод предназначен для проверки наличия в ГИС МТ указанного КИ с криптографической частью. Метод ограничен по частоте запросов (допустимая частота запросов метода - 2 секунды) и количеству КИ в запросе (максимальное количество КИ в запросе - 1000) и не предназначен для вызова с ККТ при сканировании КИ при розничной реализации."
    },
    {
      "url": "/cises/history",
      "method": "POST",
      "description": "Тип приватности: публичный (с использованием токена)."
    },
    {
      "url": "/cises/history/list",
      "method": "POST",
      "description": "Тип приватности: публичный"
    },
    {
      "url": "/api/v4/true-api/tn-ved/search",
      "method": "POST",
      "description": "Тип приватности: c токеном авторизации"
    },
    {
      "url": "/api/v4/true-api/product/info",
      "method": "POST",
      "description": "Тип приватности: публичный"
    },
    {
      "url": "/product/gtin",
      "method": "GET",
      "description": "Метод возвращает список кодов товаров с возможностью указания параметров фильтрации в запросе. Для товарной группы «Альтернативная табачная продукция» в ответе отсутствует информация по кодам товаров, добавленным с помощью пользовательского интерфейса или через «Метод создания и обновления товаров» раздела «Методы «Национального каталога»». Тип приватности: приватный"
    },
    {
      "url": "/api/v4/true-api/rd/list",
      "method": "POST",
      "description": "Тип приватности: публичный"
    },
    {
      "url": "/agreement-registry/agreement",
      "method": "POST",
      "description": "Тип приватности: приватный"
    },
    {
      "url": "/agreement-registry/cancellation",
      "method": "POST",
      "description": "Покупатели продукции (Оптовик, Розница)."
    },
    {
      "url": "/agreement-registry/agreement/list",
      "method": "GET",
      "description": "Оператор."
    },
    {
      "url": "agreement-registry/publish",
      "method": "POST",
      "description": "Тип приватности: приватный."
    },
    {
      "url": "/agreement-registry/trusted/{ownerInn}/list",
      "method": "GET",
      "description": "Оператор."
    },
    {
      "url": "/agreement-registry/trusted/{ownerInn}",
      "method": "GET",
      "description": "Тип приватности: публичный (с использованием токена)."
    },
    {
      "url": "agreement-registry/agreement/{id}/trusted-inns",
      "method": "GET",
      "description": "Оператор."
    },
    {
      "url": "/cises/gz/info",
      "method": "POST",
      "description": "Тип приватности: публичный"
    },
    {
      "url": "/warehouse/balance",
      "method": "POST",
      "description": "Тип приватности: приватный"
    },
    {
      "url": "/warehouse/operations",
      "method": "POST",
      "description": "Тип приватности: приватный"
    },
    {
      "url": "/api/v3/true-api/product/gtin-weight/cis-count",
      "method": "POST",
      "description": "Тип приватности: c токеном авторизации участника оборота товаров или Оператора ЭДО."
    },
    {
      "url": "/api/v4/true-api/doc/list",
      "method": null,
      "description": "6.1. Метод получения списка загруженных документов в ГИС МТ"
    },
    {
      "url": "/api/v3/true-api/receipt/search",
      "method": "POST",
      "description": "Тип приватности: приватный"
    },
    {
      "url": "/api/v4/true-api/receipt/list",
      "method": "GET",
      "description": "Тип приватности: приватный"
    },
    {
      "url": "/api/v4/true-api/doc/{docId}/info",
      "method": null,
      "description": "Для товарной группы «Духи и туалетная вода» метод возвращает в ответе только КИ из тела документа (см. «Справочник «Типы документов»») без отражения информации о КИ дочерних вложений, входящих в состав агрегирующих КИ: параметры «count_children» и «children» в ответе остаются скрытыми."
    },
    {
      "url": "/api/v4/true-api/receipt/{receiptId}/info",
      "method": null,
      "description": "Получение ошибок по чекам доступно в \"Метод получения квитанции результата обработки чека по идентификатору чека\"."
    },
    {
      "url": "/document/reprocess",
      "method": "POST",
      "description": "Тип приватности: приватный"
    },
    {
      "url": "/doc/validator/create",
      "method": "POST",
      "description": "Тип приватности: публичный"
    },
    {
      "url": "/doc/validator/status",
      "method": "POST",
      "description": "Тип приватности: публичный"
    },
    {
      "url": "/doc/cises",
      "method": null,
      "description": "«Перемаркировка», «Расформирование упаковки», «Трансформация упаковки», «Формирование АТК», «Расформирование АТК», «Вывод из оборота», «Возврат в оборот», «Отгрузка из ЕАЭС с признанием КИ», «Отгрузка из ЕАЭС», «Приёмка отгрузки из ЕАЭС»."
    },
    {
      "url": "/documents/edo/tpr/ud",
      "method": "GET",
      "description": "Метод возвращает квитанцию результата обработки документов (УПД, УПД(и), УКД, УКД(и), УПД (отгрузка продукции) и предложения об аннулировании УД) в ГИС МТ, которые были отправлены с 15 июля 2020 года. Запрос направляется по одному документу."
    },
    {
      "url": "/receipt/documents",
      "method": "GET",
      "description": "Тип приватности: публичный"
    },
    {
      "url": "dispenser/tasks",
      "method": null,
      "description": "В случае отсутствия подписанного договора при запросе данных возвращается ошибка 403 (отсутствует доступ к данным, не подписан договор о предоставлении сведений)."
    },
    {
      "url": "dispenser/tasks",
      "method": null,
      "description": "Выгрузка предназначена для запроса сведений по ошибкам обработки документов прямой подачи сведений и ЭДО. В параметрах запроса необходимо передать массив идентификаторов документов. Ограничение по количеству запрашиваемых документов: 1000. Для документов ЭДО передаётся полный идентификатор, равный значению, указываемому в \"ИдФайл\" документа * .xml. Для документов прямой подачи сведений передаётся идентификатор, присвоенный ГИС МТ."
    },
    {
      "url": "dispenser/tasks",
      "method": null,
      "description": "Вывод сведений о КИ осуществляется с учётом установленных фильтров в параметре «params» («Строка параметров задания на выгрузку в формате * .json»)."
    },
    {
      "url": "dispenser/tasks",
      "method": null,
      "description": "Вывод сведений осуществляется с учётом установленных фильтров в параметре «params» («Строка параметров задания на выгрузку в формате * .json»)."
    },
    {
      "url": "dispenser/tasks",
      "method": null,
      "description": "Вывод сведений о документах осуществляется с учётом установленных фильтров в параметре «params» («Строка параметров задания на выгрузку в формате * .json»)."
    },
    {
      "url": "dispenser/tasks",
      "method": null,
      "description": "Сведения о товарах формируются только для потребительской упаковки. При этом в расчётах не учитываются данные, связанные с перемаркированными товарами и остатками товаров."
    },
    {
      "url": "dispenser/tasks",
      "method": null,
      "description": "Вывод сведений о документах осуществляется с учётом установленных фильтров в параметре «params» («Строка параметров задания в формате * .json»)."
    },
    {
      "url": "dispenser/tasks",
      "method": null,
      "description": "Вывод сведений осуществляется с учётом установленных фильтров в параметре «params» («Строка параметров задания на выгрузку в формате * .json»). Если по заданным фильтрам не было найдено ни одно ограничение, то выгрузка будет пустой."
    },
    {
      "url": "dispenser/tasks",
      "method": "POST",
      "description": "Тип приватности: приватный"
    },
    {
      "url": "dispenser/tasks/{taskId}",
      "method": null,
      "description": "Метод предназначен для получения статуса задания на выгрузку по идентификатору задания, полученному в ответе метода «Метод создания нового задания на выгрузку»."
    },
    {
      "url": "dispenser/tasks",
      "method": null,
      "description": "8.5.1. Метод получения статусов заданий на выгрузку"
    },
    {
      "url": "dispenser/results",
      "method": null,
      "description": "Данный метод позволяет получить список результирующих идентификаторов выгрузок для скачивания сформированных файлов с данными."
    },
    {
      "url": "dispenser/results/{resultId}/file",
      "method": null,
      "description": "Метод \tпредоставляет \tвозможность \tскачивания \tвыгрузки \tв \tстатусе \t«COMPLETED» («Выполнено») по идентификатору выгрузки, полученному в ответе метода «Метод получения результирующих ID выгрузок данных»."
    },
    {
      "url": "dispenser/tasktypes/available_count?taskTypeShortName=краткое \tназвание \tтипа выгрузки&pg=название товарной группы",
      "method": null,
      "description": "Метод предназначен для получения информации о числе доступных выгрузок за день по типу задания и товарной группе."
    },
    {
      "url": "dispenser/tasktypes/reports/{report_id}/available_count?pg=название товарной группы",
      "method": null,
      "description": "Метод предназначен для получения информации о числе доступных выгрузок за день по отчёту и товарной группе."
    },
    {
      "url": "/api/v3/true-api/dispenser/results/{resultId}",
      "method": "DELETE",
      "description": "Тип приватности: приватный"
    },
    {
      "url": "/api/v4/true-api/edo/inn/{inn}",
      "method": "GET",
      "description": "Если участник оборота товаров зарегистрирован в ЭДО Лайт, и в качестве основного ЭДО провайдера указан ЭДО Лайт, то возвращается идентификатор участника оборота товаров вместе с префиксом «2LT-» формата «2LT-<ID участника обмена ЭДО Лайт>» (например: 2LT-572279911)."
    },
    {
      "url": "",
      "method": null,
      "description": "Тип приватности: приватный."
    },
    {
      "url": "/nk/attributes",
      "method": "GET",
      "description": "Тип приватности: публичный"
    },
    {
      "url": "/nk/brands",
      "method": "GET",
      "description": "Тип приватности: публичный"
    },
    {
      "url": "/nk/linked-accounts",
      "method": "POST",
      "description": "Тип приватности: приватный"
    },
    {
      "url": "/nk/linked-accounts-sign",
      "method": "POST",
      "description": "Тип приватности: приватный"
    },
    {
      "url": "/nk/linked-accounts-documents",
      "method": "POST",
      "description": "Тип приватности: приватный"
    },
    {
      "url": "/nk/categories",
      "method": "GET",
      "description": "Тип приватности: публичный"
    },
    {
      "url": "/nk/product",
      "method": "GET",
      "description": "Тип приватности: публичный"
    },
    {
      "url": "/nk/short-product",
      "method": "GET",
      "description": "Тип приватности: публичный"
    },
    {
      "url": "/nk/feed-product",
      "method": "GET",
      "description": "Тип приватности: публичный"
    },
    {
      "url": "/nk/feed-product-sign-pkcs",
      "method": "POST",
      "description": "Тип приватности: приватный"
    },
    {
      "url": "/nk/feed-product-document",
      "method": "POST",
      "description": "Тип приватности: публичный"
    },
    {
      "url": "/nk/feed-product-sign",
      "method": "POST",
      "description": "Тип приватности: публичный"
    },
    {
      "url": "/nk/etagslist",
      "method": "GET",
      "description": "Тип приватности: приватный"
    },
    {
      "url": "/nk/image",
      "method": "GET",
      "description": "Тип приватности: публичный"
    },
    {
      "url": "/nk/generate-gtins",
      "method": "GET",
      "description": "Тип приватности: публичный"
    },
    {
      "url": "/nk/feed",
      "method": "POST",
      "description": "Тип приватности: публичный"
    },
    {
      "url": "/nk/feed-status",
      "method": "GET",
      "description": "Тип приватности: публичный"
    },
    {
      "url": "/nk/feed-moderation",
      "method": "GET",
      "description": "Тип приватности: публичный"
    },
    {
      "url": "/nk/mark-check",
      "method": "POST",
      "description": "В одном запросе не может быть суммарно указано более 100 КИ и кодов ТН ВЭД."
    },
    {
      "url": "/nk/linked-gtins",
      "method": "GET",
      "description": "Тип приватности: публичный"
    },
    {
      "url": "/auth/simpleSignIn/идентификатор внешнего подключения",
      "method": "POST",
      "description": "Для \tполучения \tтокена \tдля \tСУЗ \tв \tстроке \tзапроса \tуказывается \tпараметр «omsConnection» — уникальный \tидентификатор \tсоединения \t(внешнего \tподключения), присвоенный зарегистрированной установке интеграционного решения."
    }
  ]
}